e6xdb/__init__.py
e6xdb/common.py
e6xdb/constants.py
e6xdb/datainputstream.py
e6xdb/date_time_utils.py
e6xdb/e6x.py
e6xdb/exceptions.py
e6xdb/sqlalchemy_e6x.py
e6xdb/typeId.py
e6xdb/server/QueryEngineService.py
e6xdb/server/__init__.py
e6xdb/server/constants.py
e6xdb/server/ttypes.py
e6xdb-1.2.38.dist-info/METADATA
e6xdb-1.2.38.dist-info/WHEEL
e6xdb-1.2.38.dist-info/entry_points.txt
e6xdb-1.2.38.dist-info/top_level.txt
e6xdb-1.2.38.dist-info/RECORD
