Metadata-Version: 2.1
Name: e6xdb
Version: 1.2.38
Summary: UNKNOWN
Home-page: UNKNOWN
Author: Uniphi, Inc.
Author-email: info@e6data.io
License: UNKNOWN
Platform: UNKNOWN
Classifier: Operating System :: POSIX :: Linux
Classifier: License :: OSI Approved :: MIT License
Classifier: Programming Language :: Python :: 3.5
Classifier: Programming Language :: Python :: 3.6
Classifier: Programming Language :: Python :: 3.7
Classifier: Programming Language :: Python :: 3.8
Classifier: Programming Language :: Python :: 3.9
Requires-Dist: sqlalchemy (>=1.0.0)
Requires-Dist: future
Requires-Dist: python-dateutil
Requires-Dist: pycryptodome
Requires-Dist: pytz
Requires-Dist: thrift
